setup.cfg
setup.py
filterql/__init__.py
filterql/exceptions.py
filterql/lookup.py
filterql/lookup_types.py
filterql/serializers.py
filterql/utils.py
filterql/validators.py
filterql.egg-info/PKG-INFO
filterql.egg-info/SOURCES.txt
filterql.egg-info/dependency_links.txt
filterql.egg-info/requires.txt
filterql.egg-info/top_level.txt