Metadata-Version: 1.1
Name: filterql
Version: 0.1
Summary: Filter queries to json and back
Home-page: https://github.com/wearespindle/filterql
Author: Devhouse Spindle
Author-email: opensource@wearespindle.com
License: MIT License
Platform: UNKNOWN
Classifier: Development Status :: 3 - Alpha
Classifier: Intended Audience :: Developers
Classifier: License :: OSI Approved :: MIT License
Classifier: Programming Language :: Python :: 2.7
Classifier: Programming Language :: Python :: 3.3
Classifier: Programming Language :: Python :: 3.4
Classifier: Programming Language :: Python :: 3.5
